.gitignore
README.md
requirements.txt
setup.cfg
setup.py
error_alerts/__init__.py
error_alerts.egg-info/PKG-INFO
error_alerts.egg-info/SOURCES.txt
error_alerts.egg-info/dependency_links.txt
error_alerts.egg-info/requires.txt
error_alerts.egg-info/top_level.txt