Metadata-Version: 2.1
Name: error-alerts
Version: 3.7
Summary: Error alerts via Telegram
Home-page: https://github.com/xjxckk/error-alerts/
Download-URL: https://github.com/xjxckk/error-alerts/archive/refs/tags/v2.tar.gz
